{"products":[{"id":1,"name":"Croissant, Raw - Mini","price":"918.05","image":"http://dummyimage.com/146x100.png/ff4444/ffffff"},
{"id":2,"name":"Lemon Grass","price":"207.16","image":"http://dummyimage.com/219x100.png/dddddd/000000"},
{"id":3,"name":"Sherry - Dry","price":"246.75","image":"http://dummyimage.com/131x100.png/cc0000/ffffff"},
{"id":4,"name":"Sprouts - Corn","price":"740.49","image":"http://dummyimage.com/209x100.png/dddddd/000000"},
{"id":5,"name":"Wine - Riesling Alsace Ac 2001","price":"184.71","image":"http://dummyimage.com/241x100.png/dddddd/000000"},
{"id":6,"name":"Pork - Loin, Bone - In","price":"476.63","image":"http://dummyimage.com/218x100.png/ff4444/ffffff"},
{"id":7,"name":"Mushroom - Crimini","price":"384.44","image":"http://dummyimage.com/128x100.png/dddddd/000000"},
{"id":8,"name":"Bonito Flakes - Toku Katsuo","price":"324.98","image":"http://dummyimage.com/141x100.png/dddddd/000000"},
{"id":9,"name":"Cookie Chocolate Chip With","price":"175.17","image":"http://dummyimage.com/235x100.png/dddddd/000000"},
{"id":10,"name":"Cheese - Parmesan Cubes","price":"362.12","image":"http://dummyimage.com/144x100.png/ff4444/ffffff"},
{"id":11,"name":"Asparagus - Mexican","price":"548.35","image":"http://dummyimage.com/179x100.png/cc0000/ffffff"},
{"id":12,"name":"Fudge - Chocolate Fudge","price":"153.80","image":"http://dummyimage.com/194x100.png/cc0000/ffffff"},
{"id":13,"name":"Sugar - Palm","price":"771.60","image":"http://dummyimage.com/233x100.png/5fa2dd/ffffff"},
{"id":14,"name":"Sugar - Monocystal / Rock","price":"785.77","image":"http://dummyimage.com/170x100.png/cc0000/ffffff"},
{"id":15,"name":"Beer - True North Lager","price":"523.38","image":"http://dummyimage.com/111x100.png/5fa2dd/ffffff"},
{"id":16,"name":"Wine - Merlot Vina Carmen","price":"413.27","image":"http://dummyimage.com/245x100.png/cc0000/ffffff"},
{"id":17,"name":"Chick Peas - Dried","price":"420.46","image":"http://dummyimage.com/179x100.png/ff4444/ffffff"},
{"id":18,"name":"Cheese - Stilton","price":"493.18","image":"http://dummyimage.com/186x100.png/5fa2dd/ffffff"},
{"id":19,"name":"Potatoes - Idaho 100 Count","price":"480.44","image":"http://dummyimage.com/211x100.png/cc0000/ffffff"},
{"id":20,"name":"Snapple - Mango Maddness","price":"606.79","image":"http://dummyimage.com/127x100.png/ff4444/ffffff"},
{"id":21,"name":"Bread - Ciabatta Buns","price":"316.56","image":"http://dummyimage.com/225x100.png/dddddd/000000"},
{"id":22,"name":"Truffle Paste","price":"889.33","image":"http://dummyimage.com/188x100.png/cc0000/ffffff"},
{"id":23,"name":"Table Cloth 62x114 White","price":"531.89","image":"http://dummyimage.com/139x100.png/cc0000/ffffff"},
{"id":24,"name":"Shiratamako - Rice Flour","price":"642.30","image":"http://dummyimage.com/197x100.png/cc0000/ffffff"},
{"id":25,"name":"Pail With Metal Handle 16l White","price":"816.65","image":"http://dummyimage.com/150x100.png/ff4444/ffffff"},
{"id":26,"name":"Appetizer - Southwestern","price":"251.67","image":"http://dummyimage.com/218x100.png/cc0000/ffffff"},
{"id":27,"name":"Pasta - Linguini, Dry","price":"990.87","image":"http://dummyimage.com/115x100.png/dddddd/000000"},
{"id":28,"name":"Pork - Bacon,back Peameal","price":"297.14","image":"http://dummyimage.com/172x100.png/cc0000/ffffff"},
{"id":29,"name":"Paper - Brown Paper Mini Cups","price":"714.52","image":"http://dummyimage.com/139x100.png/5fa2dd/ffffff"},
{"id":30,"name":"Mustard - Dry, Powder","price":"713.99","image":"http://dummyimage.com/234x100.png/dddddd/000000"},
{"id":31,"name":"Soup - Campbells Mushroom","price":"88.36","image":"http://dummyimage.com/162x100.png/cc0000/ffffff"},
{"id":32,"name":"Fond - Chocolate","price":"146.86","image":"http://dummyimage.com/159x100.png/5fa2dd/ffffff"},
{"id":33,"name":"Apple - Fuji","price":"20.54","image":"http://dummyimage.com/111x100.png/5fa2dd/ffffff"},
{"id":34,"name":"Roe - White Fish","price":"708.38","image":"http://dummyimage.com/239x100.png/5fa2dd/ffffff"},
{"id":35,"name":"Creme De Menth - White","price":"630.14","image":"http://dummyimage.com/140x100.png/cc0000/ffffff"},
{"id":36,"name":"Yogurt - Raspberry, 175 Gr","price":"484.53","image":"http://dummyimage.com/181x100.png/cc0000/ffffff"},
{"id":37,"name":"Appetizer - Tarragon Chicken","price":"512.46","image":"http://dummyimage.com/146x100.png/5fa2dd/ffffff"},
{"id":38,"name":"Black Currants","price":"339.61","image":"http://dummyimage.com/209x100.png/5fa2dd/ffffff"},
{"id":39,"name":"Vinegar - Tarragon","price":"201.35","image":"http://dummyimage.com/178x100.png/5fa2dd/ffffff"},
{"id":40,"name":"Snails - Large Canned","price":"187.18","image":"http://dummyimage.com/219x100.png/dddddd/000000"},
{"id":41,"name":"Tuna - Sushi Grade","price":"679.22","image":"http://dummyimage.com/157x100.png/dddddd/000000"},
{"id":42,"name":"Nantucket - Carrot Orange","price":"274.52","image":"http://dummyimage.com/101x100.png/cc0000/ffffff"},
{"id":43,"name":"Compound - Pear","price":"137.12","image":"http://dummyimage.com/145x100.png/ff4444/ffffff"},
{"id":44,"name":"Oysters - Smoked","price":"332.16","image":"http://dummyimage.com/169x100.png/cc0000/ffffff"},
{"id":45,"name":"Ginsing - Fresh","price":"307.95","image":"http://dummyimage.com/102x100.png/ff4444/ffffff"},
{"id":46,"name":"Tomato Paste","price":"862.57","image":"http://dummyimage.com/221x100.png/cc0000/ffffff"},
{"id":47,"name":"Shrimp - Tiger 21/25","price":"337.89","image":"http://dummyimage.com/145x100.png/dddddd/000000"},
{"id":48,"name":"Godiva White Chocolate","price":"79.83","image":"http://dummyimage.com/209x100.png/cc0000/ffffff"},
{"id":49,"name":"Wine - Casablanca Valley","price":"698.14","image":"http://dummyimage.com/201x100.png/cc0000/ffffff"},
{"id":50,"name":"Wine - Spumante Bambino White","price":"470.42","image":"http://dummyimage.com/196x100.png/5fa2dd/ffffff"},
{"id":51,"name":"Green Scrubbie Pad H.duty","price":"545.69","image":"http://dummyimage.com/177x100.png/dddddd/000000"},
{"id":52,"name":"Paper - Brown Paper Mini Cups","price":"515.13","image":"http://dummyimage.com/109x100.png/dddddd/000000"},
{"id":53,"name":"Flower - Commercial Spider","price":"133.21","image":"http://dummyimage.com/151x100.png/dddddd/000000"},
{"id":54,"name":"Hersey Shakes","price":"735.52","image":"http://dummyimage.com/142x100.png/dddddd/000000"},
{"id":55,"name":"Beef - Flank Steak","price":"90.30","image":"http://dummyimage.com/213x100.png/ff4444/ffffff"},
{"id":56,"name":"Cheese - Cheddar, Mild","price":"673.64","image":"http://dummyimage.com/112x100.png/dddddd/000000"},
{"id":57,"name":"Lemonade - Natural, 591 Ml","price":"124.93","image":"http://dummyimage.com/124x100.png/ff4444/ffffff"},
{"id":58,"name":"Wine - Remy Pannier Rose","price":"840.17","image":"http://dummyimage.com/109x100.png/dddddd/000000"},
{"id":59,"name":"Soap - Mr.clean Floor Soap","price":"155.32","image":"http://dummyimage.com/218x100.png/dddddd/000000"},
{"id":60,"name":"Evaporated Milk - Skim","price":"522.96","image":"http://dummyimage.com/244x100.png/ff4444/ffffff"},
{"id":61,"name":"Versatainer Nc - 888","price":"178.78","image":"http://dummyimage.com/143x100.png/ff4444/ffffff"},
{"id":62,"name":"Orange - Tangerine","price":"885.27","image":"http://dummyimage.com/103x100.png/5fa2dd/ffffff"},
{"id":63,"name":"Chicken - Thigh, Bone In","price":"700.79","image":"http://dummyimage.com/153x100.png/ff4444/ffffff"},
{"id":64,"name":"Wine - Magnotta, Merlot Sr Vqa","price":"82.95","image":"http://dummyimage.com/187x100.png/dddddd/000000"},
{"id":65,"name":"Pasta - Fett Alfredo, Single Serve","price":"132.29","image":"http://dummyimage.com/215x100.png/ff4444/ffffff"},
{"id":66,"name":"Juice - Ocean Spray Kiwi","price":"290.54","image":"http://dummyimage.com/122x100.png/ff4444/ffffff"},
{"id":67,"name":"Cheese - Shred Cheddar / Mozza","price":"671.92","image":"http://dummyimage.com/214x100.png/dddddd/000000"},
{"id":68,"name":"Wine - Cahors Ac 2000, Clos","price":"944.53","image":"http://dummyimage.com/161x100.png/dddddd/000000"},
{"id":69,"name":"Potatoes - Pei 10 Oz","price":"630.55","image":"http://dummyimage.com/201x100.png/cc0000/ffffff"},
{"id":70,"name":"Wine - White, Concha Y Toro","price":"786.54","image":"http://dummyimage.com/137x100.png/cc0000/ffffff"},
{"id":71,"name":"Bread - White Epi Baguette","price":"88.17","image":"http://dummyimage.com/175x100.png/5fa2dd/ffffff"},
{"id":72,"name":"Thyme - Lemon, Fresh","price":"778.38","image":"http://dummyimage.com/240x100.png/dddddd/000000"},
{"id":73,"name":"Pork Loin Bine - In Frenched","price":"285.79","image":"http://dummyimage.com/123x100.png/dddddd/000000"},
{"id":74,"name":"Flavouring Vanilla Artificial","price":"981.97","image":"http://dummyimage.com/237x100.png/cc0000/ffffff"},
{"id":75,"name":"Wine - White, Colubia Cresh","price":"143.04","image":"http://dummyimage.com/150x100.png/ff4444/ffffff"},
{"id":76,"name":"Sunflower Seed Raw","price":"557.90","image":"http://dummyimage.com/143x100.png/cc0000/ffffff"},
{"id":77,"name":"Coffee - Espresso","price":"907.19","image":"http://dummyimage.com/190x100.png/cc0000/ffffff"},
{"id":78,"name":"Prunes - Pitted","price":"782.76","image":"http://dummyimage.com/233x100.png/cc0000/ffffff"},
{"id":79,"name":"Muffin Hinge 117n","price":"805.61","image":"http://dummyimage.com/120x100.png/5fa2dd/ffffff"},
{"id":80,"name":"Foam Espresso Cup Plain White","price":"482.72","image":"http://dummyimage.com/217x100.png/dddddd/000000"},
{"id":81,"name":"Shopper Bag - S - 4","price":"732.85","image":"http://dummyimage.com/193x100.png/5fa2dd/ffffff"},
{"id":82,"name":"Peach - Fresh","price":"860.31","image":"http://dummyimage.com/104x100.png/cc0000/ffffff"},
{"id":83,"name":"Dill Weed - Dry","price":"153.73","image":"http://dummyimage.com/226x100.png/ff4444/ffffff"},
{"id":84,"name":"Ranchero - Primerba, Paste","price":"120.26","image":"http://dummyimage.com/117x100.png/dddddd/000000"},
{"id":85,"name":"Carbonated Water - Blackcherry","price":"449.08","image":"http://dummyimage.com/192x100.png/dddddd/000000"},
{"id":86,"name":"Ice Cream Bar - Hageen Daz To","price":"147.71","image":"http://dummyimage.com/104x100.png/5fa2dd/ffffff"},
{"id":87,"name":"Ice Cream - Chocolate","price":"303.39","image":"http://dummyimage.com/105x100.png/ff4444/ffffff"},
{"id":88,"name":"Lamb Rack Frenched Australian","price":"360.20","image":"http://dummyimage.com/112x100.png/dddddd/000000"},
{"id":89,"name":"Wine - Fume Blanc Fetzer","price":"943.28","image":"http://dummyimage.com/169x100.png/dddddd/000000"},
{"id":90,"name":"Shrimp - Baby, Cold Water","price":"208.74","image":"http://dummyimage.com/125x100.png/dddddd/000000"},
{"id":91,"name":"Apple - Fuji","price":"769.36","image":"http://dummyimage.com/132x100.png/ff4444/ffffff"},
{"id":92,"name":"Garlic - Primerba, Paste","price":"874.68","image":"http://dummyimage.com/225x100.png/ff4444/ffffff"},
{"id":93,"name":"Nut - Pistachio, Shelled","price":"674.16","image":"http://dummyimage.com/146x100.png/ff4444/ffffff"},
{"id":94,"name":"Pastry - Plain Baked Croissant","price":"558.81","image":"http://dummyimage.com/185x100.png/dddddd/000000"},
{"id":95,"name":"Cheese - Montery Jack","price":"544.65","image":"http://dummyimage.com/209x100.png/cc0000/ffffff"},
{"id":96,"name":"Beets","price":"357.29","image":"http://dummyimage.com/114x100.png/5fa2dd/ffffff"},
{"id":97,"name":"Oranges - Navel, 72","price":"414.81","image":"http://dummyimage.com/247x100.png/cc0000/ffffff"},
{"id":98,"name":"Juice Peach Nectar","price":"357.89","image":"http://dummyimage.com/216x100.png/dddddd/000000"},
{"id":99,"name":"Cream Of Tartar","price":"236.25","image":"http://dummyimage.com/216x100.png/ff4444/ffffff"},
{"id":100,"name":"Kellogs All Bran Bars","price":"38.99","image":"http://dummyimage.com/161x100.png/5fa2dd/ffffff"}]}